{
  "id": 19,
  "key": "Warwick",
  "name": "Warwick",
  "title": "the Uncaged Wrath of Zaun",
  "fullName": "",
  "resource": "MANA",
  "attackType": "MELEE",
  "adaptiveType": "PHYSICAL_DAMAGE",
  "stats": {
    "health": {
      "flat": 550,
      "percent": 0.0,
      "unique": 0.0,
      "uniquePercent": 0.0,
      "perLevel": 85,
      "percentPerLevel": 0.0,
      "percentBase": 0.0,
      "percentBonus": 0.0
    },
    "healthRegen": {
      "flat": 4,
      "percent": 0.0,
      "unique": 0.0,
      "uniquePercent": 0.0,
      "perLevel": 0.75,
      "percentPerLevel": 0.0,
      "percentBase": 0.0,
      "percentBonus": 0.0
    },
    "mana": {
      "flat": 280,
      "percent": 0.0,
      "unique": 0.0,
      "uniquePercent": 0.0,
      "perLevel": 35,
      "percentPerLevel": 0.0,
      "percentBase": 0.0,
      "percentBonus": 0.0
    },
    "manaRegen": {
      "flat": 7.466,
      "percent": 0.0,
      "unique": 0.0,
      "uniquePercent": 0.0,
      "perLevel": 0.575,
      "percentPerLevel": 0.0,
      "percentBase": 0.0,
      "percentBonus": 0.0
    },
    "armor": {
      "flat": 33,
      "percent": 0.0,
      "unique": 0.0,
      "uniquePercent": 0.0,
      "perLevel": 3.2,
      "percentPerLevel": 0.0,
      "percentBase": 0.0,
      "percentBonus": 0.0
    },
    "magicResistance": {
      "flat": 32.1,
      "percent": 0.0,
      "unique": 0.0,
      "uniquePercent": 0.0,
      "perLevel": 1.25,
      "percentPerLevel": 0.0,
      "percentBase": 0.0,
      "percentBonus": 0.0
    },
    "attackDamage": {
      "flat": 65,
      "percent": 0.0,
      "unique": 0.0,
      "uniquePercent": 0.0,
      "perLevel": 3,
      "percentPerLevel": 0.0,
      "percentBase": 0.0,
      "percentBonus": 0.0
    },
    "movespeed": {
      "flat": 335,
      "percent": 0.0,
      "unique": 0.0,
      "uniquePercent": 0.0,
      "perLevel": 0.0,
      "percentPerLevel": 0.0,
      "percentBase": 0.0,
      "percentBonus": 0.0
    },
    "acquisitionRadius": 400,
    "selectionRadius": 111.111099243164,
    "pathingRadius": 35,
    "gameplayRadius": 55,
    "criticalStrike": {
      "flat": 0.0,
      "percent": 200,
      "unique": 0.0,
      "uniquePercent": 0.0,
      "perLevel": 0.0,
      "percentPerLevel": 0.0,
      "percentBase": 0.0,
      "percentBonus": 0.0
    },
    "criticalStrikeModifier": 1.0,
    "attackSpeed": {
      "flat": 0.638,
      "percent": 0.0,
      "unique": 0.0,
      "uniquePercent": 0.0,
      "perLevel": 2.3,
      "percentPerLevel": 0.0,
      "percentBase": 0.0,
      "percentBonus": 0.0
    },
    "attackSpeedRatio": 0.638000011444091,
    "attackCastTime": 0.3,
    "attackTotalTime": 1.6,
    "attackDelayOffset": -0.125,
    "attackRange": {
      "flat": 125,
      "percent": 0.0,
      "unique": 0.0,
      "uniquePercent": 0.0,
      "perLevel": 0,
      "percentPerLevel": 0.0,
      "percentBase": 0.0,
      "percentBonus": 0.0
    },
    "aramDamageTaken": 0.92,
    "aramDamageDealt": 1.0,
    "aramHealing": 1.0,
    "aramShielding": 1.0,
    "urfDamageTaken": 1.0,
    "urfDamageDealt": 1.0,
    "urfHealing": 1.0,
    "urfShielding": 1.0
  },
  "roles": [
    "DIVER",
    "FIGHTER",
    "TANK"
  ],
  "attributeRatings": {
    "damage": 2,
    "toughness": 2,
    "control": 2,
    "mobility": 1,
    "utility": 1,
    "abilityReliance": 30,
    "attack": 9,
    "defense": 5,
    "magic": 3,
    "difficulty": 1
  },
  "abilities": {
    "P": [
      {
        "name": "Eternal Hunger",
        "effects": [
          {
            "description": "Innate: Warwick's basic attacks deal 10 \u2212 44 (based on level)  bonus magic damage on-hit.",
            "icon": "Eternal Hunger.png",
            "leveling": []
          },
          {
            "description": "While  below 50% maximum health he is also  healed by the amount of post-mitigation damage Eternal Hunger deals. This healing is increased[ by 150% ][ to 25 \u2212 110 (based on level) ]while  below 25% maximum health.",
            "icon": null,
            "leveling": []
          }
        ],
        "cost": null,
        "cooldown": null,
        "targeting": "Passive",
        "affects": "Self",
        "spellshieldable": "False",
        "resource": null,
        "damageType": "MAGIC_DAMAGE",
        "spellEffects": "Heal",
        "projectile": null,
        "onHitEffects": null,
        "occurrence": null,
        "notes": "The enhanced attack will apply other on-hit effects and can  critically strike as normal (the bonus damage cannot).\n Eternal Hunger does not affect structures.",
        "blurb": "Warwick's basic attacks deal bonus magic damage. If Warwick is below 50% health, he heals the same amount. If Warwick is below 25% health, this healing triples.",
        "missileSpeed": null,
        "rechargeRate": null,
        "collisionRadius": null,
        "tetherRadius": null,
        "onTargetCdStatic": null,
        "innerRadius": null,
        "speed": null,
        "width": null,
        "angle": null,
        "castTime": null,
        "effectRadius": null,
        "targetRange": null
      }
    ],
    "Q": [
      {
        "name": "Jaws of the Beast",
        "effects": [
          {
            "description": "Active: Warwick  dashes  unstoppably to the target enemy and bites them, dealing magic damage, applying  on-hit and on-attack effects and  healing himself for a portion of the post-mitigation damage dealt. The on-hits apply after the healing is calculated.",
            "icon": "Jaws of the Beast.png",
            "leveling": [
              {
                "attribute": "Magic Damage",
                "modifiers": [
                  {
                    "values": [
                      120,
                      120,
                      120,
                      120,
                      120
                    ],
                    "units": [
                      "% AD",
                      "% AD",
                      "% AD",
                      "% AD",
                      "% AD"
                    ]
                  },
                  {
                    "values": [
                      100,
                      100,
                      100,
                      100,
                      100
                    ],
                    "units": [
                      "% AP",
                      "% AP",
                      "% AP",
                      "% AP",
                      "% AP"
                    ]
                  },
                  {
                    "values": [
                      6,
                      7,
                      8,
                      9,
                      10
                    ],
                    "units": [
                      "% of target's maximum health",
                      "% of target's maximum health",
                      "% of target's maximum health",
                      "% of target's maximum health",
                      "% of target's maximum health"
                    ]
                  }
                ]
              },
              {
                "attribute": "Healing Percentage",
                "modifiers": [
                  {
                    "values": [
                      30,
                      45,
                      60,
                      75,
                      90
                    ],
                    "units": [
                      "%",
                      "%",
                      "%",
                      "%",
                      "%"
                    ]
                  }
                ]
              }
            ]
          },
          {
            "description": "If Jaws of the Beast is held, Warwick will lock his teeth into his target and use them to swing himself around to their far side. Warwick is  unable to act while swinging around his target, and will move wherever they move until he jumps off. Warwick is unstoppable while attached to an enemy.",
            "icon": null,
            "leveling": []
          }
        ],
        "cost": {
          "modifiers": [
            {
              "values": [
                50,
                60,
                70,
                80,
                90
              ],
              "units": [
                "",
                "",
                "",
                "",
                ""
              ]
            }
          ]
        },
        "cooldown": {
          "modifiers": [
            {
              "values": [
                6,
                6,
                6,
                6,
                6
              ],
              "units": [
                "",
                "",
                "",
                "",
                ""
              ]
            }
          ],
          "affectedByCdr": false
        },
        "targeting": "Unit",
        "affects": "Enemies, Self",
        "spellshieldable": "True",
        "resource": "MANA",
        "damageType": "MAGIC_DAMAGE",
        "spellEffects": "spell",
        "projectile": null,
        "onHitEffects": "True",
        "occurrence": null,
        "notes": "The ability will not cancel if the target dies during its cast time.\n Warwick cannot be  displaced while attached to an enemy, but can be  knocked down prior to reaching them.\n The button must be held until Warwick reaches his target to trigger the second effect. \n While Jaws of the Beast does not use Quick Casting by default, click-and-hold is comparable to the input required to use  Piercing Arrow or  Decimating Smash while using Quick Casting. It does not accept two-click input (e.g. First Cast and Second Cast) that Standard Casters will be used to on the aforementioned abilities.\n The distance traveled past the target depends on how long the ability was held after Warwick reached the target.",
        "blurb": "Warwick lunges forward and bites his target, dealing damage based on their maximum health and healing for damage dealt.",
        "missileSpeed": null,
        "rechargeRate": null,
        "collisionRadius": null,
        "tetherRadius": null,
        "onTargetCdStatic": null,
        "innerRadius": null,
        "speed": null,
        "width": null,
        "angle": null,
        "castTime": null,
        "effectRadius": null,
        "targetRange": "350"
      }
    ],
    "W": [
      {
        "name": "Blood Hunt",
        "effects": [
          {
            "description": "Passive: Warwick senses all enemy  champions below  below 50% of their maximum health, marking them as Blood Hunted as well as highlighting their position to his team. Warwick additionally sees a \"blood trail\" highlighting the shortest path to the Blood Hunted target, and gains  bonus movement speed while following it.",
            "icon": "Blood Hunt.png",
            "leveling": [
              {
                "attribute": "Bonus Movement Speed",
                "modifiers": [
                  {
                    "values": [
                      35,
                      40,
                      45,
                      50,
                      55
                    ],
                    "units": [
                      "%",
                      "%",
                      "%",
                      "%",
                      "%"
                    ]
                  }
                ]
              },
              {
                "attribute": "Enhanced Movement Speed",
                "modifiers": [
                  {
                    "values": [
                      87.5,
                      100,
                      112.5,
                      125,
                      137.5
                    ],
                    "units": [
                      "%",
                      "%",
                      "%",
                      "%",
                      "%"
                    ]
                  }
                ]
              }
            ]
          },
          {
            "description": "Warwick also gains  bonus attack speed upon attacking a Blood Hunted target or an enemy unit  below 50% of their maximum health.",
            "icon": null,
            "leveling": [
              {
                "attribute": "Bonus Attack Speed",
                "modifiers": [
                  {
                    "values": [
                      70,
                      80,
                      90,
                      100,
                      110
                    ],
                    "units": [
                      "%",
                      "%",
                      "%",
                      "%",
                      "%"
                    ]
                  }
                ]
              },
              {
                "attribute": "Enhanced Attack Speed",
                "modifiers": [
                  {
                    "values": [
                      175,
                      200,
                      225,
                      250,
                      275
                    ],
                    "units": [
                      "%",
                      "%",
                      "%",
                      "%",
                      "%"
                    ]
                  }
                ]
              }
            ]
          },
          {
            "description": "The bonus movement and attack speed is increased by 150% against enemies  below 20% maximum health.",
            "icon": null,
            "leveling": []
          },
          {
            "description": "Active: Warwick briefly senses all enemies and then Blood Hunts the nearest enemy champion within a large radius for 8 seconds, regardless of their  current health.",
            "icon": "Warwick Blood Hunt Mark.png",
            "leveling": []
          },
          {
            "description": "After being in combat with a champion, Blood Hunt may only be activated passively for 3 seconds. Its bonus movement speed will also be lost for 0.5 seconds, but will build up again every 0.25 seconds over the next 3.5 seconds.",
            "icon": null,
            "leveling": []
          }
        ],
        "cost": {
          "modifiers": [
            {
              "values": [
                70,
                70,
                70,
                70,
                70
              ],
              "units": [
                "",
                "",
                "",
                "",
                ""
              ]
            }
          ]
        },
        "cooldown": {
          "modifiers": [
            {
              "values": [
                120,
                105,
                90,
                75,
                60
              ],
              "units": [
                "",
                "",
                "",
                "",
                ""
              ]
            }
          ],
          "affectedByCdr": false
        },
        "targeting": "Auto",
        "affects": "Self / Enemies",
        "spellshieldable": "False",
        "resource": "MANA",
        "damageType": null,
        "spellEffects": null,
        "projectile": null,
        "onHitEffects": null,
        "occurrence": null,
        "notes": "Enemies who are Blood Hunted will display a red wolf mark on their heads while ominous music will replace their Summoner's Rift default chosen song until they are no longer Blood Hunted, with a small delay.\n Blood Hunt can detect and target decoys.\n The blood trail, altough described as a trail, does not indicate where the target has been - only the quickest route to their current location, and it will update as you and/or the target move.\n Warwick will lose his movement speed bonus if enemies that are not Blood Hunted stay exactly between him and the Blood Hunted target.\n Blood Hunt's passive only senses enemies that go below the health threshold while Warwick is alive. A unit that went below 50% health while Warwick was dead and has not taken damage while he is alive will not be detected by Blood Hunt until it falls low again.\n Same applies to enemy champions that went under the threshold by taking Nexus Obelisk damage or to units that spawn with their current health below the threshold (i.e  Hallucinate,  Mirror Image).\n\n The detection from Blood Hunt is more similar to  Tremor Sense than a form of sight - it grants positional information only. It does not explicitly inform Warwick about who is low health or if they are alone.",
        "blurb": "Warwick senses enemies below 50% health, gaining movement speed toward and attack speed against them. When they fall below 20% health, he frenzies and these bonuses triple.",
        "missileSpeed": null,
        "rechargeRate": null,
        "collisionRadius": null,
        "tetherRadius": null,
        "onTargetCdStatic": null,
        "innerRadius": null,
        "speed": null,
        "width": null,
        "angle": null,
        "castTime": null,
        "effectRadius": null,
        "targetRange": "Global / 4000"
      }
    ],
    "E": [
      {
        "name": "Primal Howl",
        "effects": [
          {
            "description": "First Cast: Warwick reduces all incoming damage received for 2.5 seconds. After 1 second, Primal Howl can be re-activated, and automatically does so after 2.5 seconds.",
            "icon": "Primal Howl.png",
            "leveling": [
              {
                "attribute": "Damage Reduction",
                "modifiers": [
                  {
                    "values": [
                      35,
                      40,
                      45,
                      50,
                      55
                    ],
                    "units": [
                      "%",
                      "%",
                      "%",
                      "%",
                      "%"
                    ]
                  }
                ]
              }
            ]
          },
          {
            "description": "Second Cast: Warwick unleashes a howl, ending the damage reduction in the process, and causing all nearby enemies to  flee for 1 second as well as  slowing them by 90%.",
            "icon": "Primal Howl 2.png",
            "leveling": []
          },
          {
            "description": "Landing  Infinite Duress will instantly reactivate Primal Howl without prematurely ending the damage reduction buff.",
            "icon": null,
            "leveling": []
          }
        ],
        "cost": {
          "modifiers": [
            {
              "values": [
                40,
                40,
                40,
                40,
                40
              ],
              "units": [
                "",
                "",
                "",
                "",
                ""
              ]
            }
          ]
        },
        "cooldown": {
          "modifiers": [
            {
              "values": [
                15,
                14,
                13,
                12,
                11
              ],
              "units": [
                "",
                "",
                "",
                "",
                ""
              ]
            }
          ],
          "affectedByCdr": false
        },
        "targeting": "Auto",
        "affects": "Enemies",
        "spellshieldable": "True",
        "resource": "MANA",
        "damageType": null,
        "spellEffects": null,
        "projectile": null,
        "onHitEffects": null,
        "occurrence": null,
        "notes": "The second activation will cancel Warwick's basic attack.\n Warwick cannot attack during the animation.",
        "blurb": "Warwick gains damage reduction for 2.5 seconds. At the end, or if re-activated, he howls, causing nearby enemies to flee for 1 second.",
        "missileSpeed": null,
        "rechargeRate": null,
        "collisionRadius": null,
        "tetherRadius": null,
        "onTargetCdStatic": null,
        "innerRadius": null,
        "speed": null,
        "width": null,
        "angle": null,
        "castTime": null,
        "effectRadius": "375",
        "targetRange": null
      }
    ],
    "R": [
      {
        "name": "Infinite Duress",
        "effects": [
          {
            "description": "Active: Warwick  leaps  unstoppably in the target direction,  suppressing the first enemy  champion he collides with for 1.5 seconds.",
            "icon": "Infinite Duress.png",
            "leveling": []
          },
          {
            "description": "Warwick  channels while the target is  suppressed, dealing magic damage by hitting the target up to 6 times while also applying  on-hit and on-attack effects up to 3 times. Infinite Duress  heals Warwick for all the damage dealt.",
            "icon": null,
            "leveling": [
              {
                "attribute": "Total Magic Damage",
                "modifiers": [
                  {
                    "values": [
                      175,
                      350,
                      525
                    ],
                    "units": [
                      "",
                      "",
                      ""
                    ]
                  },
                  {
                    "values": [
                      167,
                      167,
                      167
                    ],
                    "units": [
                      "% bonus AD",
                      "% bonus AD",
                      "% bonus AD"
                    ]
                  }
                ]
              }
            ]
          }
        ],
        "cost": {
          "modifiers": [
            {
              "values": [
                100,
                100,
                100
              ],
              "units": [
                "",
                "",
                ""
              ]
            }
          ]
        },
        "cooldown": {
          "modifiers": [
            {
              "values": [
                110,
                90,
                70
              ],
              "units": [
                "",
                "",
                ""
              ]
            }
          ],
          "affectedByCdr": false
        },
        "targeting": "Direction",
        "affects": "Enemies",
        "spellshieldable": "True",
        "resource": "MANA",
        "damageType": "MAGIC_DAMAGE",
        "spellEffects": "spell",
        "projectile": null,
        "onHitEffects": "True",
        "occurrence": null,
        "notes": "There is a brief delay before the leap and the target suppression can begin.\n The dash will be  interrupted instantly if an enemy  blinks in front of Warwick.\n The minimum range of the ability is 275 units, based on the minimum movement speed that a champion can have (110) while still being able to move. The \"base\" range of this ability is 837.5 because of his 335 base movement speed.\n Considering movement speed soft caps, with  Blood Hunt, this range increases to 1112 / 1145.5 / 1179 / 1203.125 / 1224.0625, further increased to 1360.15625 / 1412.5 / 1464.84375 / 1517.1875 / 1569.53125 against enemy champions below 20% health.\n\n The 6 hits are done in cycles of 2 hits every 0.5 seconds. The first hit deals 2/9 of the total damage and triggers the on-hit effects once while the second hit deals 1/9 of it.\n The healing is increased by  life steal.\n If Warwick does not collide with a champion, he will slide a fixed distance past the maximum range during which he is  disarmed and unable to cast movement abilities, including  Flash, but being able to cast  Jaws of the Beast and  Blood Hunt, with the former also interrupting the slide.\n Warwick is able to cast  Primal Howl at any time during the leap.",
        "blurb": "Warwick leaps in a direction (scaling with his bonus movement speed), suppressing the first champion he collides with for 1.5 seconds.",
        "missileSpeed": null,
        "rechargeRate": null,
        "collisionRadius": null,
        "tetherRadius": null,
        "onTargetCdStatic": null,
        "innerRadius": null,
        "speed": null,
        "width": null,
        "angle": null,
        "castTime": null,
        "effectRadius": null,
        "targetRange": "250% of average movement speed in the last 2.5 seconds"
      }
    ]
  },
  "releaseDate": "2009-02-21",
  "releasePatch": "lpha Week 2",
  "patchLastChanged": "10.1",
  "price": {
    "blueEssence": 450,
    "rp": 260
  }
}