{
  "name": "Guardian's Orb",
  "id": 3112,
  "tier": 1,
  "buildsFrom": [],
  "buildsInto": [],
  "noEffects": false,
  "removed": false,
  "icon": "http://ddragon.leagueoflegends.com/cdn/10.5.1/img/item/3112.png",
  "nicknames": [],
  "passives": [],
  "active": [],
  "auras": [],
  "stats": {
    "abilityPower": {
      "flat": 35.0,
      "percent": 0.0,
      "perLevel": 0.0,
      "percentPerLevel": 0.0,
      "percentBase": 0.0,
      "percentBonus": 0.0
    },
    "health": {
      "flat": 150.0,
      "percent": 0.0,
      "perLevel": 0.0,
      "percentPerLevel": 0.0,
      "percentBase": 0.0,
      "percentBonus": 0.0
    },
    "manaRegen": {
      "flat": 10.0,
      "percent": 0.0,
      "perLevel": 0.0,
      "percentPerLevel": 0.0,
      "percentBase": 0.0,
      "percentBonus": 0.0
    }
  },
  "shop": {
    "priceTotal": 950,
    "priceCombined": 0,
    "priceSell": 380,
    "tags": [
      "STARTER ITEMS:LANING",
      "DEFENSE:HEALTH",
      "MAGIC:ABILITY_POWER",
      "MAGIC:MANA_REGEN"
    ]
  }
}