{
  "name": "Devourer",
  "itemID": null,
  "tier": "Tier 3",
  "type": "Tier 3",
  "recipe": [
    "Recurve Bow"
  ],
  "builds": [],
  "noEffects": false,
  "removed": true,
  "nickname": "",
  "passives": [
    {
      "unique": true,
      "name": "Devouring",
      "effects": "Takedowns grant Devourer stacks, increasing on-hit magic damage by +1."
    },
    {
      "unique": true,
      "name": null,
      "effects": "Stacks on takedown:\n+1 for champions and large monsters.\n+2 for  Rift Scuttlers and  Rift Herald.\n+5 for  Dragon,  Baron and  Vilemaw."
    },
    {
      "unique": false,
      "name": null,
      "effects": "Transforms into  Sated Devourer at 30 Devourer stacks."
    },
    {
      "unique": false,
      "name": null,
      "effects": "30 on-hit magic damage"
    }
  ],
  "auras": [],
  "active": [],
  "stats": {
    "abilityPower": 0,
    "armor": 0,
    "armorPenetration": 0,
    "attackDamage": 0,
    "attackSpeed": 40,
    "cdr": 0,
    "cdrUnique": 0,
    "crit": 0,
    "critUnique": 0,
    "goldPer10": 0,
    "healShield": 0,
    "health": 0,
    "healthRegen": 0,
    "healthRegenFlat": 0,
    "lifesteal": 0,
    "magicPenetration": 0,
    "magicResist": 0,
    "mana": 0,
    "manaRegenPer5": 0,
    "manaRegenPer5Flat": 0,
    "moveSpeed": 0,
    "moveSpeedUnique": 0,
    "moveSpeedFlat": 0
  },
  "shop": {
    "priceFull": 1450,
    "priceCombined": 450,
    "priceSell": 1715,
    "itemTags": [
      "ATTACK:ATTACK_SPEED",
      "ATTACK:DAMAGE"
    ]
  }
}