{
  "name": "Athene's Unholy Grail",
  "itemID": 3174,
  "tier": "Tier 3",
  "type": "Tier 3",
  "recipe": [
    "Fiendish Codex",
    " Chalice of Harmony"
  ],
  "builds": [],
  "noEffects": false,
  "removed": false,
  "nickname": "",
  "passives": [
    {
      "unique": true,
      "name": null,
      "effects": " Gain 35% of the premitigation damage dealt to champions as Blood Charges, up to 100- 250 (based on level). Healing or shielding another ally consumes charges equal to 100% of the heal or shield, to heal them, up to the original effect amount."
    }
  ],
  "auras": [
    null
  ],
  "active": [
    null
  ],
  "stats": {
    "abilityPower": 30,
    "armor": 0,
    "armorPenetration": 0,
    "attackDamage": 0,
    "attackSpeed": 0,
    "cdr": 10,
    "cdrUnique": 0,
    "crit": 0,
    "critUnique": 0,
    "goldPer10": 0,
    "healShield": 0,
    "health": 0,
    "healthRegen": 0,
    "healthRegenFlat": 0,
    "lifesteal": 0,
    "magicPenetration": 0,
    "magicResist": 30,
    "mana": 0,
    "manaRegenPer5": 100,
    "manaRegenPer5Flat": 0,
    "moveSpeed": 0,
    "moveSpeedUnique": 0,
    "moveSpeedFlat": 0
  },
  "shop": {
    "priceFull": 2100,
    "priceCombined": 400,
    "priceSell": 1470,
    "itemTags": [
      "DEFENSE:MAGIC_RESIST",
      "MAGIC:ABILITY_POWER",
      "MAGIC:MANA_REGEN",
      "MAGIC:COOLDOWN_REDUCTION"
    ]
  }
}