{
  "name": "Titanic Hydra",
  "itemID": "3748",
  "tier": "Tier 3",
  "type": "Tier 3",
  "recipe": "Tiamat, Ruby Crystal, Jaurim's Fist",
  "builds": "",
  "effects": {
    "passive1": {
      "unique": true,
      "name": " Cleave",
      "effects": " Basic attacks deal 5 (+ 1% maximum health) bonus physical damage on-hit. Additionally, basic attacks also deal 40 (+ 2.5% maximum health) physical damage in a cone to units behind the target."
    },
    "passive2": null,
    "passive3": null,
    "passive4": null,
    "passive5": null,
    "active": {
      "unique": true,
      "name": " Crescent",
      "effects": " On your next basic attack, Cleave will instead deal 40 (+ 10% maximum health) to all targets and has a larger cone (20 second cooldown). Crescent resets your autoattack timer."
    },
    "aura": null,
    "aura2": null,
    "aura3": null,
    "noEffects": ""
  },
  "stats": {
    "abilityPower": "",
    "armor": "",
    "armorPenetration": "",
    "attackDamage": "40",
    "attackSpeed": "",
    "cdr": "",
    "cdrUnique": "",
    "crit": "",
    "critUnique": "",
    "goldPer10": "",
    "healShield": "",
    "health": "450",
    "healthRegen": "100",
    "healthRegenFlat": "",
    "lifesteal": "",
    "magicPenetration": "",
    "magicResist": "",
    "mana": "",
    "manaRegenPer5": "",
    "manaRegenPer5Flat": "",
    "moveSpeed": "",
    "moveSpeedUnique": "",
    "moveSpeedFlat": "",
    "spec": "",
    "spec2": ""
  },
  "shop": {
    "priceFull": "3500",
    "priceCombined": "575",
    "priceSell": "2450",
    "itemTags": {
      "tag1": "Attack:DAMAGE",
      "tag2": "Attack:None",
      "tag3": "DEFENSE:HEALTH",
      "tag4": "DEFENSE:HEALTH_REGEN",
      "tag5": null,
      "tag6": null,
      "tag7": null
    }
  },
  "other": {
    "consume": "",
    "consume2": "",
    "championItem": "",
    "limit": "Can only be purchased on  melee champions.",
    "req": "",
    "hp": "",
    "removed": false,
    "nickname": ""
  }
}